{
  "type": "ability",
  "id": "fancy_footwork",
  "name": "Fancy Footwork",
  "level": null,
  "costs": null,
  "story_text": "All combat is a dance\u2014and you'll be the one leading.",
  "keywords": [
    "Melee",
    "Strike",
    "Weapon"
  ],
  "action_type": "Main action",
  "trigger_text": null,
  "range": {
    "distance": "Melee",
    "area": null,
    "range_value": 1
  },
  "targets": "One creature",
  "power_roll": {
    "label": "Power roll",
    "characteristics": "Might or Agility",
    "tiers": {
      "low": {
        "base_damage_value": 5,
        "characteristic_damage_options": "M/A damage",
        "damage_types": null,
        "potencies": null,
        "conditions": null
      },
      "mid": {
        "base_damage_value": 7,
        "characteristic_damage_options": "M/A damage",
        "damage_types": null,
        "potencies": null,
        "conditions": "push 1"
      },
      "high": {
        "base_damage_value": 10,
        "characteristic_damage_options": "M/A damage",
        "damage_types": null,
        "potencies": null,
        "conditions": "push 2"
      }
    }
  },
  "effect": "You can shift into any square the target leaves after you push them.",
  "special_effect": null
}
