[
  {"name": "Alchemy", "group": "crafting", "description": "Make bombs and potions"},
  {"name": "Architecture", "group": "crafting", "description": "Create buildings and vehicles"},
  {"name": "Blacksmithing", "group": "crafting", "description": "Forge metal armor and weapons"},
  {"name": "Carpentry", "group": "crafting", "description": "Create items out of wood"},
  {"name": "Cooking", "group": "crafting", "description": "Create delicious dishes"},
  {"name": "Fletching", "group": "crafting", "description": "Make ranged weapons and ammunition"},
  {"name": "Forgery", "group": "crafting", "description": "Create false badges, documents, and other items"},
  {"name": "Jewelry", "group": "crafting", "description": "Create bracelets, crowns, rings, and other jewelry"},
  {"name": "Mechanics", "group": "crafting", "description": "Build machines and clockwork items"},
  {"name": "Tailoring", "group": "crafting", "description": "Craft clothing of cloth or leather"},
  {"name": "Climb", "group": "exploration", "description": "Move up vertical surfaces"},
  {"name": "Drive", "group": "exploration", "description": "Control vehicles"},
  {"name": "Endurance", "group": "exploration", "description": "Remain engaged in strenuous activity over a long period of time"},
  {"name": "Gymnastics", "group": "exploration", "description": "Move across unsteady or narrow surfaces; tumble"},
  {"name": "Heal", "group": "exploration", "description": "Use mundane first aid"},
  {"name": "Jump", "group": "exploration", "description": "Leap vertical and horizontal distances"},
  {"name": "Lift", "group": "exploration", "description": "Pick up, carry, and throw heavy objects"},
  {"name": "Navigate", "group": "exploration", "description": "Read a map and travel without becoming lost"},
  {"name": "Ride", "group": "exploration", "description": "Ride and control a nonsapient mount, such as a horse"},
  {"name": "Swim", "group": "exploration", "description": "Move through deep liquid"},
  {"name": "Brag", "group": "interpersonal", "description": "Impress others with stories of your deeds"},
  {"name": "Empathize", "group": "interpersonal", "description": "Relate to someone on a personal level"},
  {"name": "Flirt", "group": "interpersonal", "description": "Attract romantic attention from someone"},
  {"name": "Gamble", "group": "interpersonal", "description": "Make bets with others"},
  {"name": "Handle Animals", "group": "interpersonal", "description": "Interact with nonsapient animal wildlife"},
  {"name": "Interrogate", "group": "interpersonal", "description": "Obtain information from a creature withholding it"},
  {"name": "Intimidate", "group": "interpersonal", "description": "Awe or scare a creature"},
  {"name": "Lead", "group": "interpersonal", "description": "Inspire people to action"},
  {"name": "Lie", "group": "interpersonal", "description": "Convince someone that a falsehood is true"},
  {"name": "Music", "group": "interpersonal", "description": "Perform music vocally or with an instrument"},
  {"name": "Perform", "group": "interpersonal", "description": "Engage in dance, oratory, acting, or some other physical performance"},
  {"name": "Persuade", "group": "interpersonal", "description": "Convince someone to agree with you through use of your charms and grace"},
  {"name": "Read Person", "group": "interpersonal", "description": "Read the emotions and body language of other creatures"},
  {"name": "Alertness", "group": "intrigue", "description": "Intuitively sense the details of your surroundings"},
  {"name": "Conceal Object", "group": "intrigue", "description": "Hide an object on your person or in your environment"},
  {"name": "Disguise", "group": "intrigue", "description": "Change your appearance to look like a different person"},
  {"name": "Eavesdrop", "group": "intrigue", "description": "Actively listen to something that is hard to hear, such as a whispered conversation through a door"},
  {"name": "Escape Artist", "group": "intrigue", "description": "Escape from bonds such as rope or manacles"},
  {"name": "Hide", "group": "intrigue", "description": "Conceal yourself from others' observation"},
  {"name": "Pick Lock", "group": "intrigue", "description": "Open a lock without using the key"},
  {"name": "Pick Pocket", "group": "intrigue", "description": "Steal an item that another person wears or carries without them noticing"},
  {"name": "Sabotage", "group": "intrigue", "description": "Disable a mechanical device such as a trap"},
  {"name": "Search", "group": "intrigue", "description": "Actively search an environment for important details and items"},
  {"name": "Sneak", "group": "intrigue", "description": "Move silently"},
  {"name": "Track", "group": "intrigue", "description": "Follow a trail that another creature has left behind"},
  {"name": "Criminal Underworld", "group": "lore", "description": "Knowing about criminal organizations, their crimes, their relationships, and their leaders"},
  {"name": "Culture", "group": "lore", "description": "Knowing about a culture's customs, folktales, and taboos"},
  {"name": "History", "group": "lore", "description": "Knowing about significant past events"},
  {"name": "Magic", "group": "lore", "description": "Knowing about magical places, spells, rituals, items, and phenomena"},
  {"name": "Monsters", "group": "lore", "description": "Knowing monster ecology, strengths, and weaknesses"},
  {"name": "Nature", "group": "lore", "description": "Knowing about natural flora, fauna, and weather"},
  {"name": "Psionics", "group": "lore", "description": "Knowing about psionic places, spells, rituals, items, and phenomena"},
  {"name": "Religion", "group": "lore", "description": "Knowing about religious mythology, practices, and rituals"},
  {"name": "Rumors", "group": "lore", "description": "Knowing gossip, legends, and uncertain truths"},
  {"name": "Society", "group": "lore", "description": "Knowing noble etiquette and the leadership and power dynamics of noble families"},
  {"name": "Strategy", "group": "lore", "description": "Knowing about battle tactics and logistics"},
  {"name": "Timescape", "group": "lore", "description": "Knowing about the many worlds of the timescape"}
]
