{
  "classId": "class_null",
  "name": "Null",
  "type": "class",
  "starting_characteristics": {
    "motto": "“Any weapon can be turned against the hand that wields it.” — Ardashir",
    "heroicResourceName": "Discipline",
    "baseStamina": 21,
    "stamina_per_level": 9,
    "baseRecoveries": 8,
    "baseSpeed": 5,
    "baseStability": 0,
    "baseDisengage": 0,

    "potency_progression": {
      "weak": "Intuition - 2",
      "average": "Intuition - 1",
      "strong": "Intuition"
    },

    "starting_skills": {
      "granted_skills": ["Psionics"],
      "skill_groups": ["interpersonal", "lore"],
      "skill_count": 2,
      "quick_build": ["Psionics", "Read Person", "Timescape"]
    },
    "fixed_starting_characteristics": {
      "agility": 2,
      "intuition": 2
    },
    "starting_characteristics_arrays": [
      {
        "values": [2, -1, -1],
        "description": "One strong, two weaknesses"
      },
      { "values": [1, 1, -1], "description": "Two moderate, one weakness" },
      { "values": [1, 0, 0], "description": "One moderate, others neutral" }
    ],
    "levels": [
      {
        "level": 1,
        "features": [
          {
            "name": "Null Tradition",
            "type": "pick 1 subclass"
          },
          { "name": "Discipline", "type": "granted" },
          { "name": "Null Field", "type": "ability" },
          { "name": "Inertial Shield", "type": "ability" },
          { "name": "Discipline Mastery", "type": "granted" },
          { "name": "Null Speed", "type": "granted" },
          { "name": "Psionic Augmentation", "type": "pick 1" },
          { "name": "Psionic Martial Arts", "type": "granted" }
        ],
        "new_abilities": {
          "signature": 1,
          "3_cost": 1,
          "5_cost": 1
        }
      },
      {
        "level": 2,
        "features": [{ "name": "Tradition Feature", "type": "granted" }],
        "perks": [
          {
            "count": 1,
            "perk_groups": ["exploration", "interpersonal", "intrigue"]
          }
        ],
        "new_subclass_abilities": { "5_cost": 1 }
      },
      {
        "level": 3,
        "features": [
          { "name": "Psionic Leap", "type": "granted" },
          { "name": "Reorder", "type": "granted" }
        ],
        "new_abilities": { "7_cost": 1 }
      },
      {
        "level": 4,
        "features": [
          { "name": "Discipline Mastery Improvement", "type": "granted" },
          { "name": "Enhanced Null Field", "type": "granted" },
          { "name": "Regenerative Field", "type": "granted" }
        ],
        "perks": [{ "count": 1 }],
        "skills": [{ "count": 1 }],
        "characteristics": [
          { "Agility": { "setTo": 3 } },
          { "Intuition": { "setTo": 3 } }
        ]
      },
      {
        "level": 5,
        "features": [{ "name": "Tradition Feature", "type": "granted" }],
        "new_abilities": { "9_cost": 1 }
      },
      {
        "level": 6,
        "features": [
          { "name": "Elemental Absorption", "type": "granted" },
          { "name": "Elemental Buffer", "type": "granted" }
        ],
        "perks": [
          {
            "count": 1,
            "perk_groups": ["exploration", "interpersonal", "intrigue"]
          }
        ],
        "new_subclass_abilities": { "9_cost": 1 }
      },
      {
        "level": 7,
        "features": [
          { "name": "Discipline Mastery Improvement", "type": "granted" },
          { "name": "Psi Boost", "type": "granted" },
          { "name": "Improved Body", "type": "granted" }
        ],
        "skills": [{ "count": 1 }],
        "characteristics": [{ "All": { "increaseBy": 1, "max": 4 } }]
      },
      {
        "level": 8,
        "features": [{ "name": "Tradition Feature", "type": "granted" }],
        "perks": [{ "count": 1 }],
        "new_abilities": { "11_cost": 1 }
      },
      {
        "level": 9,
        "features": [{ "name": "I Am the Weapon", "type": "granted" }],
        "new_subclass_abilities": { "11_cost": 1 }
      },
      {
        "level": 10,
        "features": [
          { "name": " Discipline Mastery Improvement", "type": "granted" },
          { "name": "Manifold Body", "type": "granted" },
          { "name": "Manifold Resonance", "type": "granted" },
          { "name": "Order", "type": "granted" }
        ],
        "perks": [
          {
            "count": 1,
            "perk_groups": ["exploration", "interpersonal", "intrigue"]
          }
        ],
        "skills": [{ "count": 1 }],
        "characteristics": [
          { "Agility": { "setTo": 5 } },
          { "Intuition": { "setTo": 5 } }
        ]
      }
    ]
  }
}
